writeup/cli.py
writeup/core/evaluator.py
writeup/core/models.py
writeup/reports/json_report.py
writeup/reports/pdf_report.py
writeup/utils/text_utils.py
writeup_cv_cli-0.4.3.dist-info/METADATA
writeup_cv_cli-0.4.3.dist-info/WHEEL
writeup_cv_cli-0.4.3.dist-info/entry_points.txt
writeup_cv_cli-0.4.3.dist-info/RECORD
