Metadata-Version: 2.1
Name: writeup-cv-cli
Version: 0.4.3
Summary: A command-line CV Analyzer tool that processes PDF resumes and performs analysis.
License: MIT
Author: Yaakov Khodorkovski
Author-email: yaakov103@gmail.com
Requires-Python: >=3.10,<4.0
Classifier: License :: OSI Approved :: MIT License
Classifier: Programming Language :: Python :: 3
Classifier: Programming Language :: Python :: 3.10
Classifier: Programming Language :: Python :: 3.11
Classifier: Programming Language :: Python :: 3.12
Requires-Dist: fpdf2 (>=2.8.2,<3.0.0)
Requires-Dist: google (>=3.0.0,<4.0.0)
Requires-Dist: google-genai (>=1.3.0,<2.0.0)
Requires-Dist: httpx (>=0.28.1,<0.29.0)
Requires-Dist: matplotlib (>=3.10.1,<4.0.0)
Requires-Dist: pytest (>=8.3.5,<9.0.0)
Requires-Dist: pytest-xdist (>=3.6.1,<4.0.0)
Requires-Dist: python-dateutil (>=2.9.0.post0,<3.0.0)
Requires-Dist: python-dotenv (>=1.0.1,<2.0.0)
Requires-Dist: reportlab (>=4.3.1,<5.0.0)
Requires-Dist: requests (>=2.28.1,<3.0.0)
Requires-Dist: rich (>=13.9.4,<14.0.0)
Requires-Dist: toml (>=0.10.2,<0.11.0)
Requires-Dist: typer (>=0.9.0,<0.10.0)
Project-URL: repository, https://github.com/dolev146/writeup
